pray.py
asciicons-1.0.dist-info/LICENSE
asciicons-1.0.dist-info/METADATA
asciicons-1.0.dist-info/WHEEL
asciicons-1.0.dist-info/entry_points.txt
asciicons-1.0.dist-info/top_level.txt
asciicons-1.0.dist-info/RECORD
